h_signature/__init__.py
h_signature/h_signature_np.py
h_signature-0.0.5.dist-info/LICENSE.txt
h_signature-0.0.5.dist-info/METADATA
h_signature-0.0.5.dist-info/WHEEL
h_signature-0.0.5.dist-info/top_level.txt
h_signature-0.0.5.dist-info/RECORD
