Metadata-Version: 2.1
Name: h-signature
Version: 0.0.5
Summary: Topological H-signature
Author-email: Peter Mitrano <pmitrano@umich.edu>
Maintainer-email: Peter Mitrano <pmitrano@umich.edu>
License: Copyright (c) 2023 University of Michigan ARM Lab
Project-URL: Homepage, https://github.com/UM-ARM-Lab/h_signature
Project-URL: Bug Reports, https://github.com/UM-ARM-Lab/h_signature/issues
Project-URL: Source, https://github.com/UM-ARM-Lab/h_signature
Keywords: topology,homology,robotics
Classifier: Development Status :: 4 - Beta
Classifier: Intended Audience :: Developers
Classifier: License :: OSI Approved :: MIT License
Classifier: Programming Language :: Python :: 3
Classifier: Programming Language :: Python :: 3 :: Only
Requires-Python: >=3.6
License-File: LICENSE.txt
Requires-Dist: numpy
Provides-Extra: test
Requires-Dist: pytest ; extra == 'test'
